HelloModule/__init__.py
HelloModule/hello.py
mchp_flasher_essentials-0.0.6.dist-info/LICENSE
mchp_flasher_essentials-0.0.6.dist-info/METADATA
mchp_flasher_essentials-0.0.6.dist-info/WHEEL
mchp_flasher_essentials-0.0.6.dist-info/top_level.txt
mchp_flasher_essentials-0.0.6.dist-info/RECORD
